bimb/__init__.py
bimb-0.0.1.dist-info/LICENSE
bimb-0.0.1.dist-info/METADATA
bimb-0.0.1.dist-info/WHEEL
bimb-0.0.1.dist-info/top_level.txt
bimb-0.0.1.dist-info/RECORD
