Metadata-Version: 2.1
Name: bimb
Version: 0.0.1
Summary: bimb
Author: abhishek
Project-URL: Homepage, https://github.com/abhishekkrthakur/bimb
Project-URL: Issues, https://github.com/abhishekkrthakur/bimb/issues
Keywords: bimb
Classifier: Development Status :: 5 - Production/Stable
Classifier: License :: OSI Approved :: Apache Software License
Classifier: Operating System :: OS Independent
Classifier: Programming Language :: Python :: 3.10
Classifier: Programming Language :: Python :: 3.11
Classifier: Topic :: Scientific/Engineering :: Artificial Intelligence
License-File: LICENSE
